formula_prompt/__init__.py
formula_prompt/inputs.py
formula_prompt/navigation.py
formula_prompt/shared.py
formula_prompt-0.1.0.dist-info/LICENSE
formula_prompt-0.1.0.dist-info/METADATA
formula_prompt-0.1.0.dist-info/WHEEL
formula_prompt-0.1.0.dist-info/top_level.txt
formula_prompt-0.1.0.dist-info/RECORD
