Metadata-Version: 2.1
Name: formula-prompt
Version: 0.1.0
Summary: A small library to lets you define formulas that you can evaluate in your terminal.
Home-page: https://github.com/staadecker/formula-prompt
Author: Martin Staadecker
Author-email: machstg@gmail.com
License: UNKNOWN
Platform: UNKNOWN
Classifier: Programming Language :: Python :: 3
Classifier: License :: OSI Approved :: MIT License
Classifier: Operating System :: OS Independent
Requires-Python: >=3.6
